mutagen_helper/__init__.py
mutagen_helper/__main__.py
mutagen_helper/__version__.py
mutagen_helper/manager.py
mutagen_helper/parser.py
mutagen_helper/scanner.py
mutagen_helper/test/conftest.py
mutagen_helper/test/data/mutagen-problems.json
mutagen_helper/test/data/mutagen-problems.log
mutagen_helper/test/data/mutagen.json
mutagen_helper/test/data/mutagen.log
mutagen_helper/test/data/ret.json
mutagen_helper/test/data/test1.yml
mutagen_helper/test/data/test3.yml
mutagen_helper/test/data/test5.yml
mutagen_helper/test/data/test_auto.yml
mutagen_helper/test/data/test_auto_advanced.yml
mutagen_helper/test/data/test_auto_ignore_project_configuration.yml
mutagen_helper/test/data/test_parser_expandvars.yml
mutagen_helper/test/data/test_parser_expandvars_expected.yml
mutagen_helper/test/data/test_parser_expandvars_with_defaults.yml
mutagen_helper/test/data/test_parser_projects.yml
mutagen_helper/test/data/test_parser_projects_expected.json
mutagen_helper/test/data/test_parser_with_sessions.yml
mutagen_helper/test/data/test_parser_without_sessions.yml
mutagen_helper/test/test_manager.py
mutagen_helper/test/test_parser.py
mutagen_helper/test/test_scanner.py
mutagen_helper/test/test_wrapper.py
mutagen_helper/wrapper.py
mutagen_helper-2.0.0.dist-info/entry_points.txt
mutagen_helper-2.0.0.dist-info/LICENSE
mutagen_helper-2.0.0.dist-info/WHEEL
mutagen_helper-2.0.0.dist-info/METADATA
mutagen_helper-2.0.0.dist-info/RECORD
